vizmetrics/__init__.py
vizmetrics/src/__init__.py
vizmetrics/src/_version.py
vizmetrics/src/utils.py
vizmetrics/src/vizmetrics.py
vizmetrics/test/__init__.py
vizmetrics/test/test_vizmetrics.py
vizmetrics-0.0.1.dist-info/LICENSE
vizmetrics-0.0.1.dist-info/METADATA
vizmetrics-0.0.1.dist-info/WHEEL
vizmetrics-0.0.1.dist-info/top_level.txt
vizmetrics-0.0.1.dist-info/RECORD
